ipcx/__init__.py
ipcx/ipcx.py
ipcx/src/__init__.py
ipcx/src/client.py
ipcx/src/globals.py
ipcx/src/server.py
ipcx/src/types.py
ipcx-0.0.1.dist-info/METADATA
ipcx-0.0.1.dist-info/WHEEL
ipcx-0.0.1.dist-info/top_level.txt
ipcx-0.0.1.dist-info/RECORD
