Metadata-Version: 2.1
Name: ipcx
Version: 0.0.1
Summary: Inter Process Communication X
Author: Alex ZALO
